setup.py
distributions_racc33/Binomialdistribution.py
distributions_racc33/Gaussiandistribution.py
distributions_racc33/Generaldistribution.py
distributions_racc33/__init__.py
distributions_racc33.egg-info/PKG-INFO
distributions_racc33.egg-info/SOURCES.txt
distributions_racc33.egg-info/dependency_links.txt
distributions_racc33.egg-info/not-zip-safe
distributions_racc33.egg-info/top_level.txt