Metadata-Version: 2.1
Name: distributions-racc33
Version: 0.1
Summary: Gaussian distributions
License: UNKNOWN
Platform: UNKNOWN
